LICENSE
README.md
setup.cfg
setup.py
neuropack/__init__.py
neuropack/feature_extraction.py
neuropack/similarity_metrics.py
neuropack.egg-info/PKG-INFO
neuropack.egg-info/SOURCES.txt
neuropack.egg-info/dependency_links.txt
neuropack.egg-info/requires.txt
neuropack.egg-info/top_level.txt
neuropack/containers/__init__.py
neuropack/containers/abstract_container.py
neuropack/containers/eeg_container.py
neuropack/containers/event_container.py
neuropack/containers/live_eeg_container.py
neuropack/devices/__init__.py
neuropack/devices/base.py
neuropack/devices/brainflow.py
neuropack/keywave/__init__.py
neuropack/keywave/auth_exception.py
neuropack/keywave/operation_modes.py
neuropack/keywave/template_database.py
neuropack/preprocessing/__init__.py
neuropack/preprocessing/component_pipeline.py
neuropack/preprocessing/filters.py
neuropack/preprocessing/preprocessing_pipeline.py
neuropack/preprocessing/signal_components.py
neuropack/tasks/__init__.py
neuropack/tasks/audio_task.py
neuropack/tasks/color_task.py
neuropack/tasks/image_task.py
neuropack/tasks/multi_image_task.py
neuropack/tasks/symbol_task.py
neuropack/tasks/base/__init__.py
neuropack/tasks/base/graphic_task_base.py
neuropack/tasks/base/task_util.py
neuropack/utils/__init__.py
neuropack/utils/fast_queue.py
neuropack/utils/logging.py
neuropack/utils/marker_vault.py
neuropack/utils/recording.py