Metadata-Version: 2.1
Name: neuropack
Version: 1.0a3
Summary: Library to implement prototypes of brainwave-based authentication and to work with brainwaves in general
Home-page: https://github.com/markus-ro/neuropack
Author: Markus Röse
Author-email: mroese@mail.uni-paderborn.de
License: BSD-3-Clause
Download-URL: https://github.com/markus-ro/neuropack/archive/refs/tags/1.0a3.tar.gz
Keywords: EEG,AUTHENTICATION
Platform: UNKNOWN
Classifier: Development Status :: 3 - Alpha
Classifier: Intended Audience :: Developers
Classifier: Topic :: Security
Classifier: Topic :: Software Development
Classifier: Topic :: Scientific/Engineering
Classifier: License :: OSI Approved
Classifier: Programming Language :: Python :: 3.8
Classifier: Programming Language :: Python :: 3.9
Classifier: Programming Language :: Python :: 3.10
Classifier: Programming Language :: Python :: 3.11
License-File: LICENSE
